DDFacet/CMakeLists.txt
DDFacet/CleanSHM.py
DDFacet/DDF.py
DDFacet/MakeMovie.py
DDFacet/MemMonitor.py
DDFacet/Restore.py
DDFacet/SelfCal.py
DDFacet/TensorFlowServerFork.py
DDFacet/__init__.py
DDFacet/fits2png.py
DDFacet/plot_clean_logs.py
DDFacet/report_version.py
DDFacet/Array/ModLinAlg.py
DDFacet/Array/ModSharedArray.py
DDFacet/Array/NpParallel.py
DDFacet/Array/NpShared.py
DDFacet/Array/PrintRecArray.py
DDFacet/Array/__init__.py
DDFacet/Array/lsqnonneg.py
DDFacet/Array/shared_dict.py
DDFacet/Data/ClassBeamMean.py
DDFacet/Data/ClassData.py
DDFacet/Data/ClassFITSBeam.py
DDFacet/Data/ClassJones.py
DDFacet/Data/ClassLOFARBeam.py
DDFacet/Data/ClassMS.py
DDFacet/Data/ClassSmearMapping.py
DDFacet/Data/ClassSmoothJones.py
DDFacet/Data/ClassStokes.py
DDFacet/Data/ClassVisServer.py
DDFacet/Data/PointingProvider.py
DDFacet/Data/__init__.py
DDFacet/Data/sidereal.py
DDFacet/Gridder/CMakeLists.txt
DDFacet/Gridder/CorrelationCalculator.h
DDFacet/Gridder/DecorrelationHelper.h
DDFacet/Gridder/JonesServer.h
DDFacet/Gridder/Semaphores.h
DDFacet/Gridder/Stokes.h
DDFacet/Gridder/common.h
DDFacet/Gridder/degridder.h
DDFacet/Gridder/gridder.h
DDFacet/Gridder/old_c_gridder/CMakeLists.txt
DDFacet/Gridder/old_c_gridder/Constants.h
DDFacet/Gridder/old_c_gridder/Gridder.c
DDFacet/Gridder/old_c_gridder/Gridder.h
DDFacet/Gridder/old_c_gridder/GridderSmearPols.c
DDFacet/Gridder/old_c_gridder/GridderSmearPols.h
DDFacet/Gridder/old_c_gridder/JonesServer.c
DDFacet/Gridder/old_c_gridder/Matrix.c
DDFacet/Gridder/old_c_gridder/Semaphores.h
DDFacet/Gridder/old_c_gridder/Stokes.h
DDFacet/Gridder/old_c_gridder/Tools.h
DDFacet/Imager/ClassCasaImage.py
DDFacet/Imager/ClassDDEGridMachine.py
DDFacet/Imager/ClassDeconvMachine.py
DDFacet/Imager/ClassFacetMachine.py
DDFacet/Imager/ClassFacetMachineTessel.py
DDFacet/Imager/ClassFrequencyMachine.py
DDFacet/Imager/ClassGainMachine.py
DDFacet/Imager/ClassImToGrid.py
DDFacet/Imager/ClassImageDeconvMachine.py
DDFacet/Imager/ClassImageNoiseMachine.py
DDFacet-0.4.0.0.dist-info/LICENSE.md
DDFacet-0.4.0.0.dist-info/METADATA
DDFacet-0.4.0.0.dist-info/WHEEL
DDFacet-0.4.0.0.dist-info/top_level.txt
DDFacet-0.4.0.0.dist-info/RECORD
