Metadata-Version: 2.1
Name: DDFacet
Version: 0.4.0.0
Summary: Facet-based radio astronomy continuum imager
Home-page: http://github.com/saopicc/DDFacet
Author: Cyril Tasse
Author-email: cyril.tasse@obspm.fr
License: GNU GPL v2
Platform: UNKNOWN
Classifier: Development Status :: 4 - Beta
Classifier: Environment :: Console
Classifier: Intended Audience :: Science/Research
Classifier: License :: OSI Approved :: GNU General Public License v2 (GPLv2)
Classifier: Operating System :: POSIX :: Linux
Classifier: Programming Language :: Python
Classifier: Topic :: Scientific/Engineering :: Astronomy
Requires-Python: <3.0
Requires-Dist: nose (>=1.3.7)
Requires-Dist: Cython (>=0.25.2)
Requires-Dist: numpy (<=1.16.1)
Requires-Dist: SharedArray (>=2.0.2)
Requires-Dist: Polygon2 (>=2.0.8)
Requires-Dist: pyFFTW (>=0.10.4)
Requires-Dist: astropy (<=2.0.11)
Requires-Dist: deap (>=1.0.1)
Requires-Dist: ptyprocess (<=0.5)
Requires-Dist: ipdb (<=0.10.3)
Requires-Dist: python-casacore (>=2.1.0)
Requires-Dist: pyephem (>=3.7.6.0)
Requires-Dist: numexpr (>=2.6.2)
Requires-Dist: matplotlib (>=2.0.0)
Requires-Dist: scipy (>=0.16.0)
Requires-Dist: astLib (>=0.8.0)
Requires-Dist: psutil (>=5.2.2)
Requires-Dist: py-cpuinfo (>=3.2.0)
Requires-Dist: tables (>=3.3.0)
Requires-Dist: prettytable (>=0.7.2)
Requires-Dist: pybind11 (>=2.2.2)
Requires-Dist: pyfits (>=3.5)
Requires-Dist: configparser (<=3.5.0)
Requires-Dist: pandas (>=0.23.3)
Requires-Dist: ruamel.yaml (>=0.15.92)
